skysurvey/__init__.py
skysurvey/config.py
skysurvey/dataset.py
skysurvey/lightcurves.py
skysurvey/selection.py
skysurvey/template.py
skysurvey/data/nsns_nph1.0e+06_mejdyn0.020_mejwind0.130_phi30.txt
skysurvey/effects/__init__.py
skysurvey/effects/core.py
skysurvey/effects/hostdust.py
skysurvey/effects/milkyway.py
skysurvey/effects/scatter.py
skysurvey/examples/__init__.py
skysurvey/examples/mocksurvey.py
skysurvey/lcfit/__init__.py
skysurvey/lcfit/fit_salt.py
skysurvey/lcfit/sncutils.py
skysurvey/source/__init__.py
skysurvey/source/angular.py
skysurvey/source/complex.py
skysurvey/survey/__init__.py
skysurvey/survey/basesurvey.py
skysurvey/survey/core.py
skysurvey/survey/des.py
skysurvey/survey/healpix.py
skysurvey/survey/lsst.py
skysurvey/survey/polygon.py
skysurvey/survey/roman.py
skysurvey/survey/snls.py
skysurvey/survey/ztf.py
skysurvey/target/__init__.py
skysurvey/target/afterglow.py
skysurvey/target/collection.py
skysurvey/target/core.py
skysurvey/target/host.py
skysurvey/target/kilonova.py
skysurvey/target/rates.py
skysurvey/target/sncc.py
skysurvey/target/snia.py
skysurvey/target/stars.py
skysurvey/target/timeserie.py
skysurvey/tools/__init__.py
skysurvey/tools/blackbody.py
skysurvey/tools/download.py
skysurvey/tools/projection.py
skysurvey/tools/snana.py
skysurvey/tools/speedutils.py
skysurvey/tools/stats.py
skysurvey/tools/utils.py
skysurvey-0.27.3.dist-info/licenses/LICENSE
skysurvey-0.27.3.dist-info/METADATA
skysurvey-0.27.3.dist-info/WHEEL
skysurvey-0.27.3.dist-info/top_level.txt
skysurvey-0.27.3.dist-info/RECORD
