Metadata-Version: 2.4
Name: skysurvey
Version: 0.27.3
Summary: Simulating Transient in the sky and how to observe them
Author-email: Mickael Rigault <m.rigault@ipnl.in2p3.fr>
License-Expression: Apache-2.0
Project-URL: Homepage, https://github.com/MickaelRigault/skysurvey
Keywords: astronomy,astrophysics
Classifier: Development Status :: 3 - Alpha
Classifier: Intended Audience :: Science/Research
Classifier: Programming Language :: Python :: 3
Classifier: Topic :: Scientific/Engineering :: Astronomy
Classifier: Topic :: Scientific/Engineering :: Physics
Requires-Python: >=3.10
License-File: LICENSE
Requires-Dist: numpy>=1.26
Requires-Dist: pandas
Requires-Dist: scipy
Requires-Dist: healpy
Requires-Dist: shapely
Requires-Dist: geopandas
Requires-Dist: astropy
Requires-Dist: sncosmo
Requires-Dist: dustmaps
Requires-Dist: extinction
Requires-Dist: modeldag>=0.11.0
Requires-Dist: ztffields>=0.4.3
Provides-Extra: docs
Requires-Dist: matplotlib; extra == "docs"
Requires-Dist: myst-nb; extra == "docs"
Requires-Dist: nbsphinx; extra == "docs"
Requires-Dist: numpydoc; extra == "docs"
Requires-Dist: pandas-sphinx; extra == "docs"
Requires-Dist: sphinx-book-theme; extra == "docs"
Requires-Dist: sphinx_copybutton; extra == "docs"
Requires-Dist: sphinx-design; extra == "docs"
Provides-Extra: tests
Requires-Dist: pytest; extra == "tests"
Requires-Dist: coverage; extra == "tests"
Dynamic: license-file
